odoo9_addon_hr_contract_operating_unit-9.0.1.0.0.99.dev7-py2.7-nspkg.pth
odoo9_addon_hr_contract_operating_unit-9.0.1.0.0.99.dev7.dist-info/DESCRIPTION.rst
odoo9_addon_hr_contract_operating_unit-9.0.1.0.0.99.dev7.dist-info/METADATA
odoo9_addon_hr_contract_operating_unit-9.0.1.0.0.99.dev7.dist-info/RECORD
odoo9_addon_hr_contract_operating_unit-9.0.1.0.0.99.dev7.dist-info/WHEEL
odoo9_addon_hr_contract_operating_unit-9.0.1.0.0.99.dev7.dist-info/metadata.json
odoo9_addon_hr_contract_operating_unit-9.0.1.0.0.99.dev7.dist-info/namespace_packages.txt
odoo9_addon_hr_contract_operating_unit-9.0.1.0.0.99.dev7.dist-info/top_level.txt
odoo_addons/hr_contract_operating_unit/README.rst
odoo_addons/hr_contract_operating_unit/__init__.py
odoo_addons/hr_contract_operating_unit/__openerp__.py
odoo_addons/hr_contract_operating_unit/models/__init__.py
odoo_addons/hr_contract_operating_unit/models/hr_contract.py
odoo_addons/hr_contract_operating_unit/security/hr_contract_security.xml
odoo_addons/hr_contract_operating_unit/static/description/icon.png
odoo_addons/hr_contract_operating_unit/tests/__init__.py
odoo_addons/hr_contract_operating_unit/tests/test_hr_contract_operating_unit.py
odoo_addons/hr_contract_operating_unit/views/hr_contract_view.xml
